mymathpkg22/__init__.py
mymathpkg22/calculator.py
mymathpkg22-1.0.1.dist-info/LICENCE
mymathpkg22-1.0.1.dist-info/METADATA
mymathpkg22-1.0.1.dist-info/WHEEL
mymathpkg22-1.0.1.dist-info/top_level.txt
mymathpkg22-1.0.1.dist-info/RECORD
