Metadata-Version: 2.1
Name: mymathpkg22
Version: 1.0.1
Summary: Simple calculator package project work
Requires-Python: >=3.6
License-File: LICENCE
Provides-Extra: dev
Requires-Dist: hypothesis ; extra == 'dev'
Requires-Dist: pip-tools ; extra == 'dev'
Requires-Dist: pytest ; extra == 'dev'
